LICENSE
MANIFEST.in
README.md
setup.py
/home/ajoo/Projects/nrgb/package/src/nrgboost/tree/eval/eval.c
src/nrgboost/__init__.py
src/nrgboost/dataset.py
src/nrgboost/distribution.py
src/nrgboost/domain.py
src/nrgboost/preprocessing.py
src/nrgboost/utils.py
src/nrgboost/wrapper.py
src/nrgboost.egg-info/PKG-INFO
src/nrgboost.egg-info/SOURCES.txt
src/nrgboost.egg-info/dependency_links.txt
src/nrgboost.egg-info/requires.txt
src/nrgboost.egg-info/top_level.txt
src/nrgboost/tree/__init__.py
src/nrgboost/tree/_partitioner.py
src/nrgboost/tree/build_tree.py
src/nrgboost/tree/ensemble.py
src/nrgboost/tree/fit_tree.py
src/nrgboost/tree/generative.py
src/nrgboost/tree/partitioner.py
src/nrgboost/tree/eval/__init__.py
src/nrgboost/tree/eval/build.py
src/nrgboost/tree/eval/eval.c
src/nrgboost/tree/eval/eval.h
src/nrgboost/tree/eval/pcg-c-0.94/LICENSE.txt
src/nrgboost/tree/eval/pcg-c-0.94/README.md
src/nrgboost/tree/eval/pcg-c-0.94/extras/entropy.c
src/nrgboost/tree/eval/pcg-c-0.94/extras/entropy.h
src/nrgboost/tree/eval/pcg-c-0.94/extras/pcg_spinlock.h
src/nrgboost/tree/eval/pcg-c-0.94/include/pcg_variants.h
src/nrgboost/tree/eval/pcg-c-0.94/src/pcg-advance-128.c
src/nrgboost/tree/eval/pcg-c-0.94/src/pcg-advance-16.c
src/nrgboost/tree/eval/pcg-c-0.94/src/pcg-advance-32.c
src/nrgboost/tree/eval/pcg-c-0.94/src/pcg-advance-64.c
src/nrgboost/tree/eval/pcg-c-0.94/src/pcg-advance-8.c
src/nrgboost/tree/eval/pcg-c-0.94/src/pcg-global-32.c
src/nrgboost/tree/eval/pcg-c-0.94/src/pcg-global-64.c
src/nrgboost/tree/eval/pcg-c-0.94/src/pcg-output-128.c
src/nrgboost/tree/eval/pcg-c-0.94/src/pcg-output-16.c
src/nrgboost/tree/eval/pcg-c-0.94/src/pcg-output-32.c
src/nrgboost/tree/eval/pcg-c-0.94/src/pcg-output-64.c
src/nrgboost/tree/eval/pcg-c-0.94/src/pcg-output-8.c
src/nrgboost/tree/eval/pcg-c-0.94/src/pcg-rngs-128.c
src/nrgboost/tree/eval/pcg-c-0.94/src/pcg-rngs-16.c
src/nrgboost/tree/eval/pcg-c-0.94/src/pcg-rngs-32.c
src/nrgboost/tree/eval/pcg-c-0.94/src/pcg-rngs-64.c
src/nrgboost/tree/eval/pcg-c-0.94/src/pcg-rngs-8.c