Metadata-Version: 2.2
Name: nrgboost
Version: 0.0.2
Summary: Official NRGBoost implementation
Home-page: https://github.com/ajoo/nrgboost
Author: João Bravo
License-File: LICENSE
Requires-Dist: cffi>=1
Requires-Dist: numpy
Requires-Dist: scipy
Requires-Dist: numba
Requires-Dist: tqdm
Requires-Dist: joblib
Requires-Dist: pandas
Dynamic: author
Dynamic: description
Dynamic: description-content-type
Dynamic: home-page
Dynamic: requires-dist
Dynamic: summary
